analyse_obfuscation/__init__.py
analyse_obfuscation/helpers.py
analyse_obfuscation/output_results.py
analyse_obfuscation/run.py
analyse_obfuscation/test_process_obfuscation.py
analyse_obfuscation-1.1.0.dist-info/LICENSE
analyse_obfuscation-1.1.0.dist-info/METADATA
analyse_obfuscation-1.1.0.dist-info/WHEEL
analyse_obfuscation-1.1.0.dist-info/entry_points.txt
analyse_obfuscation-1.1.0.dist-info/top_level.txt
analyse_obfuscation-1.1.0.dist-info/RECORD
