Metadata-Version: 2.1
Name: analyse-obfuscation
Version: 1.1.0
Summary: Project for identifying executables that have command-line options that can be obfuscated, possibly bypassing detection rules.
Home-page: https://github.com/wietze/windows-command-line-obfuscation
Author: @Wietze
Classifier: Programming Language :: Python :: 3
Classifier: License :: OSI Approved :: GNU Affero General Public License v3
Classifier: Operating System :: Microsoft :: Windows
Classifier: Intended Audience :: Developers
Classifier: Intended Audience :: Information Technology
Classifier: Intended Audience :: System Administrators
Classifier: Topic :: Security
Classifier: Topic :: Internet :: Log Analysis
Classifier: Environment :: Console
License-File: LICENSE
Requires-Dist: colorama
Requires-Dist: terminaltables
Requires-Dist: tqdm
